{"data": [[[1, null, 0], [0.9099058844164382, 5.325984477996826, {"__enum__": "StatusType.SUCCESS"}, {}]], [[2, null, 0], [1.682557143649013, 0.6609861850738525, {"__enum__": "StatusType.SUCCESS"}, {}]], [[3, null, 0], [0.9011099786044913, 10.501999616622925, {"__enum__": "StatusType.SUCCESS"}, {}]], [[4, null, 0], [0.8991760987928551, 19.223909854888916, {"__enum__": "StatusType.SUCCESS"}, {}]], [[5, null, 0], [0.8979325586121772, 12.82123613357544, {"__enum__": "StatusType.SUCCESS"}, {}]], [[6, null, 0], [0.8987579235970787, 26.17963695526123, {"__enum__": "StatusType.SUCCESS"}, {}]], [[7, null, 0], [0.8978946992160441, 13.033477067947388, {"__enum__": "StatusType.SUCCESS"}, {}]], [[8, null, 0], [1.5642975947037343, 0.46900153160095215, {"__enum__": "StatusType.SUCCESS"}, {}]], [[9, null, 0], [0.8064031568155223, 6.629345655441284, {"__enum__": "StatusType.SUCCESS"}, {}]], [[10, null, 0], [0.9043952690908013, 8.088523387908936, {"__enum__": "StatusType.SUCCESS"}, {}]], [[11, null, 0], [0.8186339120565543, 3.604877233505249, {"__enum__": "StatusType.SUCCESS"}, {}]], [[12, null, 0], [0.8209931291561317, 12.27156949043274, {"__enum__": "StatusType.SUCCESS"}, {}]], [[13, null, 0], [0.8171793054558544, 9.81329345703125, {"__enum__": "StatusType.SUCCESS"}, {}]], [[14, null, 0], [2.1916070788614985, 0.4731290340423584, {"__enum__": "StatusType.SUCCESS"}, {}]], [[15, null, 0], [0.8089355878523296, 17.881378650665283, {"__enum__": "StatusType.SUCCESS"}, {}]]], "configs": {"1": {"rf_max_features": 0.5, "rf_n_estimators": 81}, "2": {"rf_max_features": 0.7, "rf_n_estimators": 8}, "3": {"rf_max_features": 0.5, "rf_n_estimators": 154}, "4": {"rf_max_features": 0.7, "rf_n_estimators": 227}, "5": {"rf_max_features": 0.5, "rf_n_estimators": 227}, "6": {"rf_max_features": 0.7, "rf_n_estimators": 300}, "7": {"rf_max_features": 0.7, "rf_n_estimators": 154}, "8": {"rf_max_features": 0.5, "rf_n_estimators": 8}, "9": {"rf_max_features": 0.3, "rf_n_estimators": 154}, "10": {"rf_max_features": 0.7, "rf_n_estimators": 81}, "11": {"rf_max_features": 0.3, "rf_n_estimators": 81}, "12": {"rf_max_features": 0.3, "rf_n_estimators": 300}, "13": {"rf_max_features": 0.3, "rf_n_estimators": 227}, "14": {"rf_max_features": 0.3, "rf_n_estimators": 8}, "15": {"rf_max_features": 0.5, "rf_n_estimators": 300}}}