{"cpu_time": 0, "total_cpu_time": null, "wallclock_time": 0.001375436782836914, "evaluations": 0, "cost": 2147483648, "incumbent": ["dimensionality_reduction=''PCA''", "feature_extraction=''haralick''", "learning_algorithm=''RF''", "haralick_distance='1'", "pca_whiten=''true''", "rf_max_features='0.5'", "rf_n_estimators='10'"]}
{"cpu_time": 79.29425501823425, "total_cpu_time": null, "wallclock_time": 79.32479763031006, "evaluations": 1, "cost": 7.89109158112653, "incumbent": ["dimensionality_reduction=''PCA''", "feature_extraction=''haralick''", "learning_algorithm=''RF''", "haralick_distance='1'", "pca_whiten=''true''", "rf_max_features='0.5'", "rf_n_estimators='10'"]}
{"cpu_time": 157.54425835609436, "total_cpu_time": null, "wallclock_time": 157.73433661460876, "evaluations": 2, "cost": 1.264618883745536, "incumbent": ["dimensionality_reduction=''PCA''", "feature_extraction=''haralick''", "learning_algorithm=''RF''", "haralick_distance='3'", "pca_whiten=''false''", "rf_max_features='0.7354015303010129'", "rf_n_estimators='186'"]}
{"cpu_time": 160.04546117782593, "total_cpu_time": null, "wallclock_time": 160.28372597694397, "evaluations": 3, "cost": 1.033636304663309, "incumbent": ["dimensionality_reduction=''PCA''", "feature_extraction=''VGG''", "learning_algorithm=''SVM''", "pca_whiten=''false''", "svm_C='54.10582404072731'", "svm_gamma='5.627505745726167'"]}
{"cpu_time": 161.31885433197021, "total_cpu_time": null, "wallclock_time": 161.73857879638672, "evaluations": 4, "cost": 1.0101349851592263, "incumbent": ["dimensionality_reduction=''ISOMAP''", "feature_extraction=''inception''", "learning_algorithm=''SVM''", "isomap_n_components='3'", "isomap_n_neighbors='7'", "svm_C='20.828008740136'", "svm_gamma='4.2639047297470345'"]}
{"cpu_time": 162.57205772399902, "total_cpu_time": null, "wallclock_time": 163.027902841568, "evaluations": 5, "cost": 1.0070366895529541, "incumbent": ["dimensionality_reduction=''ISOMAP''", "feature_extraction=''inception''", "learning_algorithm=''SVM''", "isomap_n_components='3'", "isomap_n_neighbors='7'", "svm_C='15.806048248551688'", "svm_gamma='0.7133242081569142'"]}
{"cpu_time": 167.14570593833923, "total_cpu_time": null, "wallclock_time": 167.78452038764954, "evaluations": 6, "cost": 0.7194780887801201, "incumbent": ["dimensionality_reduction=''PCA''", "feature_extraction=''VGG''", "learning_algorithm=''RF''", "pca_whiten=''true''", "rf_max_features='0.5249461832010445'", "rf_n_estimators='134'"]}
{"cpu_time": 830.6291947364807, "total_cpu_time": null, "wallclock_time": 833.5506520271301, "evaluations": 26, "cost": 0.7090350167711928, "incumbent": ["dimensionality_reduction=''PCA''", "feature_extraction=''VGG''", "learning_algorithm=''RF''", "pca_whiten=''true''", "rf_max_features='0.5396380359320223'", "rf_n_estimators='233'"]}
{"cpu_time": 2234.093068599701, "total_cpu_time": null, "wallclock_time": 2241.5468850135803, "evaluations": 63, "cost": 0.7073568323326019, "incumbent": ["dimensionality_reduction=''PCA''", "feature_extraction=''VGG''", "learning_algorithm=''RF''", "pca_whiten=''true''", "rf_max_features='0.5110021680081005'", "rf_n_estimators='274'"]}
{"cpu_time": 2802.7363600730896, "total_cpu_time": null, "wallclock_time": 2812.084130525589, "evaluations": 78, "cost": 0.706535800361903, "incumbent": ["dimensionality_reduction=''PCA''", "feature_extraction=''VGG''", "learning_algorithm=''RF''", "pca_whiten=''false''", "rf_max_features='0.41858617617620947'", "rf_n_estimators='163'"]}
{"cpu_time": 3320.017801761627, "total_cpu_time": null, "wallclock_time": 3331.6367375850677, "evaluations": 97, "cost": 0.7005045743588351, "incumbent": ["dimensionality_reduction=''PCA''", "feature_extraction=''VGG''", "learning_algorithm=''RF''", "pca_whiten=''true''", "rf_max_features='0.7894917747886201'", "rf_n_estimators='122'"]}
