{"data": [[[1, null, 0], [0.5391692898776527, 6.070641994476318, {"__enum__": "StatusType.SUCCESS"}, {}]], [[2, null, 0], [1.1762160416287406, 0.8288929462432861, {"__enum__": "StatusType.SUCCESS"}, {}]], [[3, null, 0], [0.5452639771423242, 11.303718090057373, {"__enum__": "StatusType.SUCCESS"}, {}]], [[4, null, 0], [0.5437568495695778, 22.584872722625732, {"__enum__": "StatusType.SUCCESS"}, {}]], [[5, null, 0], [0.5413799415291076, 16.663195371627808, {"__enum__": "StatusType.SUCCESS"}, {}]], [[6, null, 0], [0.5435646943823157, 30.055049419403076, {"__enum__": "StatusType.SUCCESS"}, {}]], [[7, null, 0], [0.5423483767271938, 15.3568754196167, {"__enum__": "StatusType.SUCCESS"}, {}]], [[8, null, 0], [1.2904068174020855, 0.6229557991027832, {"__enum__": "StatusType.SUCCESS"}, {}]], [[9, null, 0], [0.5452942851698046, 7.142209053039551, {"__enum__": "StatusType.SUCCESS"}, {}]], [[10, null, 0], [0.5465312786370521, 8.113928318023682, {"__enum__": "StatusType.SUCCESS"}, {}]], [[11, null, 0], [0.5363154704812514, 3.7993741035461426, {"__enum__": "StatusType.SUCCESS"}, {}]], [[12, null, 0], [0.5485680725586125, 22.191437482833862, {"__enum__": "StatusType.SUCCESS"}, {}]], [[13, null, 0], [0.5501474956301986, 13.832045793533325, {"__enum__": "StatusType.SUCCESS"}, {}]], [[14, null, 0], [1.0359774410065996, 0.42102885246276855, {"__enum__": "StatusType.SUCCESS"}, {}]], [[15, null, 0], [0.5539238902177925, 10.48865270614624, {"__enum__": "StatusType.SUCCESS"}, {}]]], "configs": {"1": {"rf_max_features": 0.5, "rf_n_estimators": 81}, "2": {"rf_max_features": 0.7, "rf_n_estimators": 8}, "3": {"rf_max_features": 0.5, "rf_n_estimators": 154}, "4": {"rf_max_features": 0.7, "rf_n_estimators": 227}, "5": {"rf_max_features": 0.5, "rf_n_estimators": 227}, "6": {"rf_max_features": 0.7, "rf_n_estimators": 300}, "7": {"rf_max_features": 0.7, "rf_n_estimators": 154}, "8": {"rf_max_features": 0.5, "rf_n_estimators": 8}, "9": {"rf_max_features": 0.3, "rf_n_estimators": 154}, "10": {"rf_max_features": 0.7, "rf_n_estimators": 81}, "11": {"rf_max_features": 0.3, "rf_n_estimators": 81}, "12": {"rf_max_features": 0.5, "rf_n_estimators": 300}, "13": {"rf_max_features": 0.3, "rf_n_estimators": 300}, "14": {"rf_max_features": 0.3, "rf_n_estimators": 8}, "15": {"rf_max_features": 0.3, "rf_n_estimators": 227}}}