{"cpu_time": 0, "total_cpu_time": null, "wallclock_time": 9.131431579589844e-05, "evaluations": 0, "cost": 2147483648, "incumbent": ["isomap_n_components='2'", "isomap_n_neighbors='5'", "rf_max_features='0.5'", "rf_n_estimators='81'"]}
{"cpu_time": 0.6573255062103271, "total_cpu_time": null, "wallclock_time": 0.672804594039917, "evaluations": 1, "cost": 0.6224854240093418, "incumbent": ["isomap_n_components='2'", "isomap_n_neighbors='5'", "rf_max_features='0.5'", "rf_n_estimators='81'"]}
{"cpu_time": 2.213512659072876, "total_cpu_time": null, "wallclock_time": 2.281404733657837, "evaluations": 3, "cost": 0.4477476408536045, "incumbent": ["isomap_n_components='2'", "isomap_n_neighbors='5'", "rf_max_features='0.7'", "rf_n_estimators='154'"]}
{"cpu_time": 3.3232944011688232, "total_cpu_time": null, "wallclock_time": 3.4449217319488525, "evaluations": 4, "cost": 0.13502593546980748, "incumbent": ["isomap_n_components='4'", "isomap_n_neighbors='4'", "rf_max_features='0.5'", "rf_n_estimators='227'"]}
{"cpu_time": 21.85413956642151, "total_cpu_time": null, "wallclock_time": 22.611063718795776, "evaluations": 22, "cost": 0.13310788250821695, "incumbent": ["isomap_n_components='4'", "isomap_n_neighbors='4'", "rf_max_features='0.7'", "rf_n_estimators='300'"]}
