{"cpu_time": 0, "total_cpu_time": null, "wallclock_time": 0.0001659393310546875, "evaluations": 0, "cost": 2147483648, "incumbent": ["dimensionality_reduction=''PCA''", "feature_extraction=''haralick''", "learning_algorithm=''RF''", "haralick_distance='1'", "pca_whiten=''true''", "rf_max_features='0.5'", "rf_n_estimators='10'"]}
{"cpu_time": 38.92533087730408, "total_cpu_time": null, "wallclock_time": 38.93961024284363, "evaluations": 1, "cost": 1.00859808768527, "incumbent": ["dimensionality_reduction=''PCA''", "feature_extraction=''haralick''", "learning_algorithm=''RF''", "haralick_distance='1'", "pca_whiten=''true''", "rf_max_features='0.5'", "rf_n_estimators='10'"]}
{"cpu_time": 78.45472455024719, "total_cpu_time": null, "wallclock_time": 78.55255722999573, "evaluations": 3, "cost": 0.8468336440875001, "incumbent": ["dimensionality_reduction=''PCA''", "feature_extraction=''VGG''", "learning_algorithm=''SVM''", "pca_whiten=''false''", "svm_C='54.10582404072731'", "svm_gamma='5.627505745726167'"]}
{"cpu_time": 80.0865044593811, "total_cpu_time": null, "wallclock_time": 80.3401050567627, "evaluations": 6, "cost": 0.6918112477261946, "incumbent": ["dimensionality_reduction=''PCA''", "feature_extraction=''VGG''", "learning_algorithm=''RF''", "pca_whiten=''true''", "rf_max_features='0.5249461832010445'", "rf_n_estimators='134'"]}
