{"cpu_time": 0, "total_cpu_time": null, "wallclock_time": 0.00019860267639160156, "evaluations": 0, "cost": 2147483648, "incumbent": ["dimensionality_reduction=''PCA''", "feature_extraction=''haralick''", "learning_algorithm=''RF''", "haralick_distance='1'", "pca_whiten=''true''", "rf_max_features='0.5'", "rf_n_estimators='81'"]}
{"cpu_time": 51.31913423538208, "total_cpu_time": null, "wallclock_time": 51.33777618408203, "evaluations": 1, "cost": 4.648672411324742, "incumbent": ["dimensionality_reduction=''PCA''", "feature_extraction=''haralick''", "learning_algorithm=''RF''", "haralick_distance='1'", "pca_whiten=''true''", "rf_max_features='0.5'", "rf_n_estimators='81'"]}
{"cpu_time": 166.7089056968689, "total_cpu_time": null, "wallclock_time": 166.92884802818298, "evaluations": 5, "cost": 0.8184169189752414, "incumbent": ["dimensionality_reduction=''naive_dimensionality_reduction''", "feature_extraction=''inception''", "learning_algorithm=''RF''", "rf_max_features='0.3'", "rf_n_estimators='300'"]}
{"cpu_time": 268.9449326992035, "total_cpu_time": null, "wallclock_time": 269.5015254020691, "evaluations": 10, "cost": 0.5538260049578588, "incumbent": ["dimensionality_reduction=''naive_dimensionality_reduction''", "feature_extraction=''VGG''", "learning_algorithm=''RF''", "rf_max_features='0.7'", "rf_n_estimators='154'"]}
{"cpu_time": 689.73304438591, "total_cpu_time": null, "wallclock_time": 692.0060012340546, "evaluations": 34, "cost": 0.5457889925718667, "incumbent": ["dimensionality_reduction=''naive_dimensionality_reduction''", "feature_extraction=''VGG''", "learning_algorithm=''RF''", "rf_max_features='0.3'", "rf_n_estimators='81'"]}
