{"cpu_time": 0, "total_cpu_time": null, "wallclock_time": 8.869171142578125e-05, "evaluations": 0, "cost": 2147483648, "incumbent": ["isomap_n_components='2'", "isomap_n_neighbors='5'", "rf_max_features='0.5'", "rf_n_estimators='81'"]}
{"cpu_time": 0.6572070121765137, "total_cpu_time": null, "wallclock_time": 0.670712947845459, "evaluations": 1, "cost": 0.5395767220120465, "incumbent": ["isomap_n_components='2'", "isomap_n_neighbors='5'", "rf_max_features='0.5'", "rf_n_estimators='81'"]}
{"cpu_time": 1.342400312423706, "total_cpu_time": null, "wallclock_time": 1.392307996749878, "evaluations": 2, "cost": 0.3828327559844588, "incumbent": ["isomap_n_components='2'", "isomap_n_neighbors='7'", "rf_max_features='0.5'", "rf_n_estimators='81'"]}
{"cpu_time": 3.3684825897216797, "total_cpu_time": null, "wallclock_time": 3.5017755031585693, "evaluations": 4, "cost": 0.13575134831584798, "incumbent": ["isomap_n_components='4'", "isomap_n_neighbors='4'", "rf_max_features='0.5'", "rf_n_estimators='227'"]}
{"cpu_time": 17.691243171691895, "total_cpu_time": null, "wallclock_time": 18.308903694152832, "evaluations": 19, "cost": 0.1349042177305577, "incumbent": ["isomap_n_components='4'", "isomap_n_neighbors='4'", "rf_max_features='0.7'", "rf_n_estimators='300'"]}
{"cpu_time": 22.11220955848694, "total_cpu_time": null, "wallclock_time": 22.961873054504395, "evaluations": 24, "cost": 0.13413772007835886, "incumbent": ["isomap_n_components='4'", "isomap_n_neighbors='4'", "rf_max_features='0.5'", "rf_n_estimators='154'"]}
{"cpu_time": 97.92535185813904, "total_cpu_time": null, "wallclock_time": 102.10226917266846, "evaluations": 115, "cost": 0.1336775360710164, "incumbent": ["isomap_n_components='4'", "isomap_n_neighbors='4'", "rf_max_features='0.3'", "rf_n_estimators='81'"]}
